adrtlib/.clang-format
adrtlib/__init__.py
adrtlib/__main__.py
adrtlib/_adrtlib.cp313-win32.pyd
adrtlib/_adrtlib.cpp
adrtlib/benchmark/adrtlib_benchmark.cpp
adrtlib/benchmark/chart.py
adrtlib/CMakeLists.txt
adrtlib/demo.py
adrtlib/include/adrtlib/adrtlib.hpp
adrtlib/include/adrtlib/common.hpp
adrtlib/include/adrtlib/common_algorithms.hpp
adrtlib/include/adrtlib/fht2d.hpp
adrtlib/include/adrtlib/fht2ids.hpp
adrtlib/include/adrtlib/fht2idt.hpp
adrtlib/include/adrtlib/non_recursive.hpp
adrtlib/README.md
adrtlib/ref/asd2/plot.py
adrtlib/ref/asd2/statistics.csv
adrtlib/ref/asd2.py
adrtlib/ref/common.py
adrtlib/ref/fht2d.py
adrtlib/ref/fht2ids.py
adrtlib/ref/fht2idt.py
adrtlib/ref/fht2ms.py
adrtlib/ref/fht2mt.py
adrtlib/ref/fht2sp.py
adrtlib/ref/fht2ss.py
adrtlib/ref/fht2st.py
adrtlib/ref/khanipov.py
adrtlib/ref/list_patterns.py
adrtlib/ref/non_recursive.py
adrtlib/ref/Patterns4numbers.py
adrtlib/test/adrtlib_test.cpp
adrtlib/testdata/SheppLogan_Phantom.png
adrtlib/testdata/SheppLogan_Phantom.svg
include/benchmark/benchmark.h
include/benchmark/export.h
include/gmock/gmock-actions.h
include/gmock/gmock-cardinalities.h
include/gmock/gmock-function-mocker.h
include/gmock/gmock-matchers.h
include/gmock/gmock-more-actions.h
include/gmock/gmock-more-matchers.h
include/gmock/gmock-nice-strict.h
include/gmock/gmock-spec-builders.h
include/gmock/gmock.h
include/gmock/internal/custom/gmock-generated-actions.h
include/gmock/internal/custom/gmock-matchers.h
include/gmock/internal/custom/gmock-port.h
include/gmock/internal/custom/README.md
include/gmock/internal/gmock-internal-utils.h
include/gmock/internal/gmock-port.h
include/gmock/internal/gmock-pp.h
include/gtest/gtest-assertion-result.h
include/gtest/gtest-death-test.h
include/gtest/gtest-matchers.h
include/gtest/gtest-message.h
include/gtest/gtest-param-test.h
include/gtest/gtest-printers.h
include/gtest/gtest-spi.h
include/gtest/gtest-test-part.h
include/gtest/gtest-typed-test.h
include/gtest/gtest.h
adrtlib-0.0.2.dist-info/METADATA
adrtlib-0.0.2.dist-info/WHEEL
adrtlib-0.0.2.dist-info/licenses/LICENSE
adrtlib-0.0.2.dist-info/RECORD
