Metadata-Version: 2.2
Name: adrtlib
Version: 0.0.2
Summary: A Set of Approximate Discrete Radon Transform functions
Author-Email: Arseniy Terekhin <senyai@gmail.com>
Classifier: License :: OSI Approved :: MIT License
Requires-Python: >=3.10
